txpool/__init__.py
txpool/pool.py
txpool/worker.py
txpool-0.9.dist-info/DESCRIPTION.rst
txpool-0.9.dist-info/METADATA
txpool-0.9.dist-info/WHEEL
txpool-0.9.dist-info/top_level.txt
txpool-0.9.dist-info/metadata.json
txpool-0.9.dist-info/RECORD
