Metadata-Version: 2.0
Name: txpool
Version: 0.9
Summary: A persistent process pool for Twisted
Home-page: https://github.com/escattone/txpool
Author: Ryan Johnson
Author-email: escattone@gmail.com
License: MIT
Platform: UNKNOWN
Classifier: Programming Language :: Python :: 2.7
Classifier: Programming Language :: Python :: 2 :: Only
Classifier: Development Status :: 4 - Beta
Classifier: Natural Language :: English
Classifier: Framework :: Twisted
Classifier: Intended Audience :: Developers
Classifier: License :: OSI Approved :: MIT License
Classifier: Operating System :: OS Independent
Classifier: Topic :: Software Development :: Libraries :: Python Modules
Requires-Dist: twisted (>=12)
